.gitignore
LICENSE
README.rst
setup.py
docs/io.rst
misc/convert_dropEst.R
scqtlib/__init__.py
scqtlib/version.py
scqtlib.egg-info/PKG-INFO
scqtlib.egg-info/SOURCES.txt
scqtlib.egg-info/dependency_links.txt
scqtlib.egg-info/requires.txt
scqtlib.egg-info/top_level.txt
scqtlib/plots/__init__.py
scqtlib/plots/base_plot.py
scqtlib/stats/__init__.py
scqtlib/stats/glm.py
scqtlib/stats/qtl.py
scqtlib/tools/__init__.py
scqtlib/tools/filter_10x_raw.py
scqtlib/utils/__init__.py
scqtlib/utils/base_utils.py
scqtlib/utils/io_utils.py
scqtlib/utils/misc_utils.py