Metadata-Version: 2.1
Name: scqtlib
Version: 0.1.4
Summary: scQTLib: single-cell quantitative trait analysis library
Home-page: https://github.com/huangyh09/scQTLib
Author: ['Yuanhua Huang']
Author-email: yuanhua@hku.hk
License: Apache-2.0
Keywords: generalised linear model,negative binomial,likelihood ratio test
License-File: LICENSE
Requires-Dist: numpy>=1.9.0
Requires-Dist: scipy>=1.4.0
Requires-Dist: matplotlib
Requires-Dist: statsmodels>=0.11.1
Provides-Extra: docs
Requires-Dist: sphinx_bootstrap_theme; extra == "docs"
